wordlike/__init__.py
wordlike/wordlike.py
wordlike-0.0.2.dist-info/LICENSE
wordlike-0.0.2.dist-info/METADATA
wordlike-0.0.2.dist-info/WHEEL
wordlike-0.0.2.dist-info/top_level.txt
wordlike-0.0.2.dist-info/RECORD
